{"name":"B1_SECRET","settings":{"physics":{"gravity":[0,-9.8,0]},"render":{"fog_end":100,"fog_start":1,"global_ambient":[1,1,1],"fog_color":[0,1,0],"fog":"none","fog_density":0.01,"gamma_correction":1,"tonemapping":0,"exposure":1,"skybox":null,"skyboxIntensity":1,"skyboxMip":0,"lightmapSizeMultiplier":16,"lightmapMaxResolution":2048,"lightmapMode":1}},"entities":{"46e49d6b-35b4-4ad4-9ac2-b8c00927a650":{"name":"Root","parent":null,"resource_id":"46e49d6b-35b4-4ad4-9ac2-b8c00927a650","tags":[],"enabled":true,"components":{},"scale":[1,1,1],"position":[0,0,0],"rotation":[0,0,0],"children":["f10ada4a-826a-4c22-b171-75921e10079b","3b5213a5-e529-4c14-9b61-5ff8d2ad8ddc","4fb0262e-d17a-46b1-806b-89185da2d62e","6bd1865c-6f49-4a41-bb16-488d48af0d94","9c02d825-555b-42df-bd40-c86b2e1ab08e","571a88be-ac7c-4cbc-9a72-a90cfab85941","fbfe8c0e-2716-443e-bacc-2ec772781b05","5254e3bd-d2b9-4bda-8a3b-8d54e05627d2","5b05dab5-6cda-46bc-a454-5400446c7118","22bd3295-c8ca-442b-8786-0580f4b2376d"]},"f10ada4a-826a-4c22-b171-75921e10079b":{"name":"Box","parent":"46e49d6b-35b4-4ad4-9ac2-b8c00927a650","resource_id":"f10ada4a-826a-4c22-b171-75921e10079b","tags":[],"enabled":true,"components":{"model":{"enabled":true,"type":"box","asset":null,"materialAsset":37001967,"castShadows":true,"receiveShadows":true,"lightmapped":false,"lightmapSizeMultiplier":1,"castShadowsLightmap":true,"isStatic":false,"layers":[0],"batchGroupId":null},"rigidbody":{"enabled":true,"type":"static","mass":1,"linearDamping":0,"angularDamping":0,"linearFactor":[1,1,1],"angularFactor":[1,1,1],"friction":0.5,"restitution":0.5},"collision":{"enabled":true,"type":"box","halfExtents":[9,9,0],"radius":0.5,"axis":1,"height":2,"asset":null}},"scale":[18,18,0.001],"position":[0,9,-9],"rotation":[0,0,0],"children":[]},"571a88be-ac7c-4cbc-9a72-a90cfab85941":{"name":"Box","parent":"46e49d6b-35b4-4ad4-9ac2-b8c00927a650","resource_id":"571a88be-ac7c-4cbc-9a72-a90cfab85941","tags":[],"enabled":true,"components":{"model":{"enabled":true,"type":"box","asset":null,"materialAsset":37001967,"castShadows":true,"receiveShadows":true,"lightmapped":false,"lightmapSizeMultiplier":1,"castShadowsLightmap":true,"isStatic":false,"layers":[0],"batchGroupId":null},"rigidbody":{"enabled":true,"type":"static","mass":1,"linearDamping":0,"angularDamping":0,"linearFactor":[1,1,1],"angularFactor":[1,1,1],"friction":0.5,"restitution":0.5},"collision":{"enabled":true,"type":"box","halfExtents":[9,0,9],"radius":0.5,"axis":1,"height":2,"asset":null}},"scale":[18,0.001,18],"position":[0,0,0],"rotation":[0,0,0],"children":[]},"22bd3295-c8ca-442b-8786-0580f4b2376d":{"name":"Player","tags":["player"],"enabled":true,"resource_id":"22bd3295-c8ca-442b-8786-0580f4b2376d","parent":"46e49d6b-35b4-4ad4-9ac2-b8c00927a650","children":["034873ba-89c3-4531-8a21-f9fb8c10561d","06559279-a940-4ef3-8b14-d22bbe567b60","080436d4-6ef0-4608-8fea-1b461ddc89d6","ed3e3211-58fb-40bc-a964-2da44a2761a3"],"position":[0,1,-8],"rotation":[0,180,0],"scale":[1,1,1],"components":{"script":{"enabled":true,"order":["firstPersonMovement"],"scripts":{"firstPersonMovement":{"enabled":true,"attributes":{"power":2500,"lookSpeed":0.25,"fov":60}}}},"rigidbody":{"enabled":true,"type":"dynamic","mass":100,"linearDamping":0.99,"angularDamping":0,"linearFactor":[1,1,1],"angularFactor":[0,0,0],"friction":0,"restitution":0},"collision":{"enabled":true,"type":"capsule","halfExtents":[0.5,0.5,0.5],"radius":0.5,"axis":1,"height":2,"asset":null},"model":{"enabled":true,"type":"capsule","asset":null,"materialAsset":null,"castShadows":false,"castShadowsLightmap":true,"receiveShadows":true,"lightmapped":false,"lightmapSizeMultiplier":1,"castShadowsLightMap":true,"lightMapped":false,"lightMapSizeMultiplier":1,"isStatic":false,"layers":[0],"batchGroupId":null}}},"034873ba-89c3-4531-8a21-f9fb8c10561d":{"name":"Camera","tags":[],"enabled":true,"resource_id":"034873ba-89c3-4531-8a21-f9fb8c10561d","parent":"22bd3295-c8ca-442b-8786-0580f4b2376d","children":[],"position":[-0.000498345769783453,0.9,0],"rotation":[0,0,0],"scale":[1,1,1],"components":{"camera":{"enabled":true,"clearColorBuffer":true,"clearColor":[0,0,0,1],"clearDepthBuffer":true,"projection":0,"fov":45,"frustumCulling":true,"orthoHeight":4,"nearClip":0.1,"farClip":1000,"priority":0,"rect":[0,0,0,0],"layers":[0,1,2,3,4]},"script":{"enabled":true,"order":[],"scripts":{}}}},"06559279-a940-4ef3-8b14-d22bbe567b60":{"name":"GoodArea","tags":[],"enabled":true,"resource_id":"06559279-a940-4ef3-8b14-d22bbe567b60","parent":"22bd3295-c8ca-442b-8786-0580f4b2376d","children":[],"position":[0,0,0],"rotation":[0,0,0],"scale":[0.943816231667995,1,1],"components":{"collision":{"enabled":true,"type":"cylinder","halfExtents":[1.5,1.5,1.5],"radius":0.5,"axis":1,"height":2,"asset":null},"script":{"enabled":true,"order":["trigger"],"scripts":{"trigger":{"enabled":true,"attributes":{"adjective":"good","maxCount":2,"wrongAdj":"bad","wrongUI":"4bd4b1e6-0c9c-4141-b6f8-bb853cc6b296","rightUI":"2db0625f-1842-4dc7-a7e4-8b1e18c3240a"}}}}}},"080436d4-6ef0-4608-8fea-1b461ddc89d6":{"name":"Point Light","tags":[],"enabled":true,"resource_id":"080436d4-6ef0-4608-8fea-1b461ddc89d6","parent":"22bd3295-c8ca-442b-8786-0580f4b2376d","children":[],"position":[0,0.9,0],"rotation":[0,0,0],"scale":[1,1,1],"components":{"light":{"enabled":true,"type":"point","bake":false,"affectDynamic":true,"affectLightmapped":false,"color":[1,1,1],"intensity":0,"castShadows":false,"shadowType":0,"vsmBlurMode":1,"vsmBlurSize":11,"vsmBias":0.01,"shadowDistance":16,"shadowResolution":256,"shadowBias":0.2,"normalOffsetBias":0.05,"range":1000000,"falloffMode":0,"innerConeAngle":40,"outerConeAngle":45,"cookieAsset":null,"cookieIntensity":1,"cookieFalloff":true,"cookieChannel":"rgb","cookieAngle":0,"cookieScale":[1,1],"cookieOffset":[0,0],"isStatic":false,"layers":[0],"bakeDir":true,"shadowUpdateMode":2}}},"ed3e3211-58fb-40bc-a964-2da44a2761a3":{"name":"SKYBOX","tags":[],"enabled":true,"resource_id":"ed3e3211-58fb-40bc-a964-2da44a2761a3","parent":"22bd3295-c8ca-442b-8786-0580f4b2376d","children":["bfab2bac-a19c-4e2b-8438-e24260c3d221","277617c2-25f0-4fdf-86cd-b40026f961fa","e58acbf9-9910-40d0-875f-694a289883ff","89205281-1daa-4b5a-95c1-7db1f4af7cfd","d0df9d4d-c9f3-479b-996a-b6d11f168067","ce599b24-b99b-4de5-8396-02a674934054","0dfe5b63-3df0-479f-838c-c276dd86e0f6","099936bc-0ebe-4b13-be7a-55781719ebe8","04bb8e44-ed12-4b9f-9c28-4a67a2d11025","0aa66b53-0aa2-42d5-90c3-462fc49e0142","4b670b2c-16a9-4ba5-850c-ef9f6fbbde0e","ac06fc86-e14f-4fc6-a431-d94d2e5eba0d","0c011034-3b01-4fb1-81ce-929aea98acb5","9e3a5731-0201-48bb-b07c-84b5f4837b3b","6cf5bbef-5765-407f-88ca-b4a061b17124","37c681b2-efde-4ccc-931b-35e3b000a69e","32a31714-1fce-4259-bfa8-fb86b5dbb16c","388ad753-ceb3-436f-b0c1-0b47c3bb121f","32b5959f-8436-48de-acf6-c278dc3b08de"],"position":[0,0,0],"rotation":[0,0,0],"scale":[1,1,1],"components":{}},"bfab2bac-a19c-4e2b-8438-e24260c3d221":{"name":"New Entity","tags":[],"enabled":true,"resource_id":"bfab2bac-a19c-4e2b-8438-e24260c3d221","parent":"ed3e3211-58fb-40bc-a964-2da44a2761a3","children":["46161981-7c72-4a1e-a2ea-dfc48c727094","6883dbb7-e4d5-4817-be9a-245c18f620f7"],"position":[0,0,0],"rotation":[0,0,0],"scale":[1,1,1],"components":{}},"46161981-7c72-4a1e-a2ea-dfc48c727094":{"name":"1","tags":[],"enabled":true,"resource_id":"46161981-7c72-4a1e-a2ea-dfc48c727094","parent":"bfab2bac-a19c-4e2b-8438-e24260c3d221","children":[],"position":[5.551115123125783e-17,0,500],"rotation":[0,180,0],"scale":[100,1000,1],"components":{"element":{"enabled":true,"type":"image","anchor":[0.5,0.5,0.5,0.5],"pivot":[0.5,0.5],"text":"","key":null,"fontAsset":37001863,"fontSize":32,"minFontSize":8,"maxFontSize":32,"autoFitWidth":false,"autoFitHeight":false,"maxLines":null,"lineHeight":32,"wrapLines":true,"spacing":1,"color":[1,1,1],"opacity":1,"textureAsset":37001908,"spriteAsset":null,"spriteFrame":0,"pixelsPerUnit":null,"width":1,"height":1,"margin":[-0.49999999999999994,-0.5,-0.5,-0.5],"alignment":[0.5,0.5],"outlineColor":[0,0,0,1],"outlineThickness":0,"shadowColor":[0,0,0,1],"shadowOffset":[0,0],"rect":[0,0,1,1],"materialAsset":null,"autoWidth":false,"autoHeight":false,"useInput":true,"batchGroupId":null,"mask":false,"layers":[4],"enableMarkup":false}}},"6883dbb7-e4d5-4817-be9a-245c18f620f7":{"name":"1","tags":[],"enabled":true,"resource_id":"6883dbb7-e4d5-4817-be9a-245c18f620f7","parent":"bfab2bac-a19c-4e2b-8438-e24260c3d221","children":[],"position":[4.601534176376919e-17,0,-500],"rotation":[0,0,0],"scale":[100,1000,1],"components":{"element":{"enabled":true,"type":"image","anchor":[0.5,0.5,0.5,0.5],"pivot":[0.5,0.5],"text":"","key":null,"fontAsset":37001863,"fontSize":32,"minFontSize":8,"maxFontSize":32,"autoFitWidth":false,"autoFitHeight":false,"maxLines":null,"lineHeight":32,"wrapLines":true,"spacing":1,"color":[1,1,1],"opacity":1,"textureAsset":37001908,"spriteAsset":null,"spriteFrame":0,"pixelsPerUnit":null,"width":1,"height":1,"margin":[-0.5,-0.5,-0.5,-0.5],"alignment":[0.5,0.5],"outlineColor":[0,0,0,1],"outlineThickness":0,"shadowColor":[0,0,0,1],"shadowOffset":[0,0],"rect":[0,0,1,1],"materialAsset":null,"autoWidth":false,"autoHeight":false,"useInput":true,"batchGroupId":null,"mask":false,"layers":[4],"enableMarkup":false}}},"277617c2-25f0-4fdf-86cd-b40026f961fa":{"name":"New Entity","tags":[],"enabled":true,"resource_id":"277617c2-25f0-4fdf-86cd-b40026f961fa","parent":"ed3e3211-58fb-40bc-a964-2da44a2761a3","children":["a41ec5ab-55fb-4735-aade-68183003a55e","e5bd3b5a-9d32-4de2-92d0-46540673d843"],"position":[0,0,0],"rotation":[0,10,0],"scale":[1,1,1],"components":{}},"a41ec5ab-55fb-4735-aade-68183003a55e":{"name":"1","tags":[],"enabled":true,"resource_id":"a41ec5ab-55fb-4735-aade-68183003a55e","parent":"277617c2-25f0-4fdf-86cd-b40026f961fa","children":[],"position":[5.551115123125783e-17,0,500],"rotation":[0,180,0],"scale":[100,1000,1],"components":{"element":{"enabled":true,"type":"image","anchor":[0.5,0.5,0.5,0.5],"pivot":[0.5,0.5],"text":"","key":null,"fontAsset":37001863,"fontSize":32,"minFontSize":8,"maxFontSize":32,"autoFitWidth":false,"autoFitHeight":false,"maxLines":null,"lineHeight":32,"wrapLines":true,"spacing":1,"color":[1,1,1],"opacity":1,"textureAsset":37001908,"spriteAsset":null,"spriteFrame":0,"pixelsPerUnit":null,"width":1,"height":1,"margin":[-0.49999999999999994,-0.5,-0.5,-0.5],"alignment":[0.5,0.5],"outlineColor":[0,0,0,1],"outlineThickness":0,"shadowColor":[0,0,0,1],"shadowOffset":[0,0],"rect":[0,0,1,1],"materialAsset":null,"autoWidth":false,"autoHeight":false,"useInput":true,"batchGroupId":null,"mask":false,"layers":[4],"enableMarkup":false}}},"e5bd3b5a-9d32-4de2-92d0-46540673d843":{"name":"1","tags":[],"enabled":true,"resource_id":"e5bd3b5a-9d32-4de2-92d0-46540673d843","parent":"277617c2-25f0-4fdf-86cd-b40026f961fa","children":[],"position":[5.551115123125783e-17,0,-500],"rotation":[0,0,0],"scale":[100,1000,1],"components":{"element":{"enabled":true,"type":"image","anchor":[0.5,0.5,0.5,0.5],"pivot":[0.5,0.5],"text":"","key":null,"fontAsset":37001863,"fontSize":32,"minFontSize":8,"maxFontSize":32,"autoFitWidth":false,"autoFitHeight":false,"maxLines":null,"lineHeight":32,"wrapLines":true,"spacing":1,"color":[1,1,1],"opacity":1,"textureAsset":37001908,"spriteAsset":null,"spriteFrame":0,"pixelsPerUnit":null,"width":1,"height":1,"margin":[-0.49999999999999994,-0.5,-0.5,-0.5],"alignment":[0.5,0.5],"outlineColor":[0,0,0,1],"outlineThickness":0,"shadowColor":[0,0,0,1],"shadowOffset":[0,0],"rect":[0,0,1,1],"materialAsset":null,"autoWidth":false,"autoHeight":false,"useInput":true,"batchGroupId":null,"mask":false,"layers":[4],"enableMarkup":false}}},"e58acbf9-9910-40d0-875f-694a289883ff":{"name":"New Entity","tags":[],"enabled":true,"resource_id":"e58acbf9-9910-40d0-875f-694a289883ff","parent":"ed3e3211-58fb-40bc-a964-2da44a2761a3","children":["25bbe7a6-1069-47a6-a74c-84e8d169b8b9","0b11d795-ddc5-4cc4-93a9-6b4c5a36f778"],"position":[0,0,0],"rotation":[0,20,0],"scale":[1,1,1],"components":{}},"25bbe7a6-1069-47a6-a74c-84e8d169b8b9":{"name":"1","tags":[],"enabled":true,"resource_id":"25bbe7a6-1069-47a6-a74c-84e8d169b8b9","parent":"e58acbf9-9910-40d0-875f-694a289883ff","children":[],"position":[5.551115123125783e-17,0,500],"rotation":[0,180,0],"scale":[100,1000,1],"components":{"element":{"enabled":true,"type":"image","anchor":[0.5,0.5,0.5,0.5],"pivot":[0.5,0.5],"text":"","key":null,"fontAsset":37001863,"fontSize":32,"minFontSize":8,"maxFontSize":32,"autoFitWidth":false,"autoFitHeight":false,"maxLines":null,"lineHeight":32,"wrapLines":true,"spacing":1,"color":[1,1,1],"opacity":1,"textureAsset":37001908,"spriteAsset":null,"spriteFrame":0,"pixelsPerUnit":null,"width":1,"height":1,"margin":[-0.49999999999999994,-0.5,-0.5,-0.5],"alignment":[0.5,0.5],"outlineColor":[0,0,0,1],"outlineThickness":0,"shadowColor":[0,0,0,1],"shadowOffset":[0,0],"rect":[0,0,1,1],"materialAsset":null,"autoWidth":false,"autoHeight":false,"useInput":true,"batchGroupId":null,"mask":false,"layers":[4],"enableMarkup":false}}},"0b11d795-ddc5-4cc4-93a9-6b4c5a36f778":{"name":"1","tags":[],"enabled":true,"resource_id":"0b11d795-ddc5-4cc4-93a9-6b4c5a36f778","parent":"e58acbf9-9910-40d0-875f-694a289883ff","children":[],"position":[5.551115123125783e-17,0,-500],"rotation":[0,0,0],"scale":[100,1000,1],"components":{"element":{"enabled":true,"type":"image","anchor":[0.5,0.5,0.5,0.5],"pivot":[0.5,0.5],"text":"","key":null,"fontAsset":37001863,"fontSize":32,"minFontSize":8,"maxFontSize":32,"autoFitWidth":false,"autoFitHeight":false,"maxLines":null,"lineHeight":32,"wrapLines":true,"spacing":1,"color":[1,1,1],"opacity":1,"textureAsset":37001908,"spriteAsset":null,"spriteFrame":0,"pixelsPerUnit":null,"width":1,"height":1,"margin":[-0.49999999999999994,-0.5,-0.5,-0.5],"alignment":[0.5,0.5],"outlineColor":[0,0,0,1],"outlineThickness":0,"shadowColor":[0,0,0,1],"shadowOffset":[0,0],"rect":[0,0,1,1],"materialAsset":null,"autoWidth":false,"autoHeight":false,"useInput":true,"batchGroupId":null,"mask":false,"layers":[4],"enableMarkup":false}}},"89205281-1daa-4b5a-95c1-7db1f4af7cfd":{"name":"New Entity","tags":[],"enabled":true,"resource_id":"89205281-1daa-4b5a-95c1-7db1f4af7cfd","parent":"ed3e3211-58fb-40bc-a964-2da44a2761a3","children":["590754f0-2338-4444-8b37-4c0c9d642d2f","e0bca109-2261-4cb3-bc85-4845bf339cd9"],"position":[0,0,0],"rotation":[0,30,0],"scale":[1,1,1],"components":{}},"590754f0-2338-4444-8b37-4c0c9d642d2f":{"name":"1","tags":[],"enabled":true,"resource_id":"590754f0-2338-4444-8b37-4c0c9d642d2f","parent":"89205281-1daa-4b5a-95c1-7db1f4af7cfd","children":[],"position":[5.551115123125783e-17,0,500],"rotation":[0,180,0],"scale":[100,1000,1],"components":{"element":{"enabled":true,"type":"image","anchor":[0.5,0.5,0.5,0.5],"pivot":[0.5,0.5],"text":"","key":null,"fontAsset":37001863,"fontSize":32,"minFontSize":8,"maxFontSize":32,"autoFitWidth":false,"autoFitHeight":false,"maxLines":null,"lineHeight":32,"wrapLines":true,"spacing":1,"color":[1,1,1],"opacity":1,"textureAsset":37001908,"spriteAsset":null,"spriteFrame":0,"pixelsPerUnit":null,"width":1,"height":1,"margin":[-0.49999999999999994,-0.5,-0.5,-0.5],"alignment":[0.5,0.5],"outlineColor":[0,0,0,1],"outlineThickness":0,"shadowColor":[0,0,0,1],"shadowOffset":[0,0],"rect":[0,0,1,1],"materialAsset":null,"autoWidth":false,"autoHeight":false,"useInput":true,"batchGroupId":null,"mask":false,"layers":[4],"enableMarkup":false}}},"e0bca109-2261-4cb3-bc85-4845bf339cd9":{"name":"1","tags":[],"enabled":true,"resource_id":"e0bca109-2261-4cb3-bc85-4845bf339cd9","parent":"89205281-1daa-4b5a-95c1-7db1f4af7cfd","children":[],"position":[5.551115123125783e-17,0,-500],"rotation":[0,0,0],"scale":[100,1000,1],"components":{"element":{"enabled":true,"type":"image","anchor":[0.5,0.5,0.5,0.5],"pivot":[0.5,0.5],"text":"","key":null,"fontAsset":37001863,"fontSize":32,"minFontSize":8,"maxFontSize":32,"autoFitWidth":false,"autoFitHeight":false,"maxLines":null,"lineHeight":32,"wrapLines":true,"spacing":1,"color":[1,1,1],"opacity":1,"textureAsset":37001908,"spriteAsset":null,"spriteFrame":0,"pixelsPerUnit":null,"width":1,"height":1,"margin":[-0.49999999999999994,-0.5,-0.5,-0.5],"alignment":[0.5,0.5],"outlineColor":[0,0,0,1],"outlineThickness":0,"shadowColor":[0,0,0,1],"shadowOffset":[0,0],"rect":[0,0,1,1],"materialAsset":null,"autoWidth":false,"autoHeight":false,"useInput":true,"batchGroupId":null,"mask":false,"layers":[4],"enableMarkup":false}}},"d0df9d4d-c9f3-479b-996a-b6d11f168067":{"name":"New Entity","tags":[],"enabled":true,"resource_id":"d0df9d4d-c9f3-479b-996a-b6d11f168067","parent":"ed3e3211-58fb-40bc-a964-2da44a2761a3","children":["f7de174a-4dbc-439f-b614-c8c40ddda2c4","e9d5f719-3e2c-40ca-a39b-79f228708283"],"position":[0,0,0],"rotation":[0,40,0],"scale":[1,1,1],"components":{}},"f7de174a-4dbc-439f-b614-c8c40ddda2c4":{"name":"1","tags":[],"enabled":true,"resource_id":"f7de174a-4dbc-439f-b614-c8c40ddda2c4","parent":"d0df9d4d-c9f3-479b-996a-b6d11f168067","children":[],"position":[5.551115123125783e-17,0,500],"rotation":[0,180,0],"scale":[100,1000,1],"components":{"element":{"enabled":true,"type":"image","anchor":[0.5,0.5,0.5,0.5],"pivot":[0.5,0.5],"text":"","key":null,"fontAsset":37001863,"fontSize":32,"minFontSize":8,"maxFontSize":32,"autoFitWidth":false,"autoFitHeight":false,"maxLines":null,"lineHeight":32,"wrapLines":true,"spacing":1,"color":[1,1,1],"opacity":1,"textureAsset":37001908,"spriteAsset":null,"spriteFrame":0,"pixelsPerUnit":null,"width":1,"height":1,"margin":[-0.49999999999999994,-0.5,-0.5,-0.5],"alignment":[0.5,0.5],"outlineColor":[0,0,0,1],"outlineThickness":0,"shadowColor":[0,0,0,1],"shadowOffset":[0,0],"rect":[0,0,1,1],"materialAsset":null,"autoWidth":false,"autoHeight":false,"useInput":true,"batchGroupId":null,"mask":false,"layers":[4],"enableMarkup":false}}},"e9d5f719-3e2c-40ca-a39b-79f228708283":{"name":"1","tags":[],"enabled":true,"resource_id":"e9d5f719-3e2c-40ca-a39b-79f228708283","parent":"d0df9d4d-c9f3-479b-996a-b6d11f168067","children":[],"position":[5.551115123125783e-17,0,-500],"rotation":[0,0,0],"scale":[100,1000,1],"components":{"element":{"enabled":true,"type":"image","anchor":[0.5,0.5,0.5,0.5],"pivot":[0.5,0.5],"text":"","key":null,"fontAsset":37001863,"fontSize":32,"minFontSize":8,"maxFontSize":32,"autoFitWidth":false,"autoFitHeight":false,"maxLines":null,"lineHeight":32,"wrapLines":true,"spacing":1,"color":[1,1,1],"opacity":1,"textureAsset":37001908,"spriteAsset":null,"spriteFrame":0,"pixelsPerUnit":null,"width":1,"height":1,"margin":[-0.49999999999999994,-0.5,-0.5,-0.5],"alignment":[0.5,0.5],"outlineColor":[0,0,0,1],"outlineThickness":0,"shadowColor":[0,0,0,1],"shadowOffset":[0,0],"rect":[0,0,1,1],"materialAsset":null,"autoWidth":false,"autoHeight":false,"useInput":true,"batchGroupId":null,"mask":false,"layers":[4],"enableMarkup":false}}},"ce599b24-b99b-4de5-8396-02a674934054":{"name":"New Entity","tags":[],"enabled":true,"resource_id":"ce599b24-b99b-4de5-8396-02a674934054","parent":"ed3e3211-58fb-40bc-a964-2da44a2761a3","children":["4011c513-0676-4b95-b9a6-9091b8b67472","6a2df091-c082-4c26-980c-04c5b520708c"],"position":[0,0,0],"rotation":[0,50,0],"scale":[1,1,1],"components":{}},"4011c513-0676-4b95-b9a6-9091b8b67472":{"name":"1","tags":[],"enabled":true,"resource_id":"4011c513-0676-4b95-b9a6-9091b8b67472","parent":"ce599b24-b99b-4de5-8396-02a674934054","children":[],"position":[5.551115123125783e-17,0,500],"rotation":[0,180,0],"scale":[100,1000,1],"components":{"element":{"enabled":true,"type":"image","anchor":[0.5,0.5,0.5,0.5],"pivot":[0.5,0.5],"text":"","key":null,"fontAsset":37001863,"fontSize":32,"minFontSize":8,"maxFontSize":32,"autoFitWidth":false,"autoFitHeight":false,"maxLines":null,"lineHeight":32,"wrapLines":true,"spacing":1,"color":[1,1,1],"opacity":1,"textureAsset":37001908,"spriteAsset":null,"spriteFrame":0,"pixelsPerUnit":null,"width":1,"height":1,"margin":[-0.49999999999999994,-0.5,-0.5,-0.5],"alignment":[0.5,0.5],"outlineColor":[0,0,0,1],"outlineThickness":0,"shadowColor":[0,0,0,1],"shadowOffset":[0,0],"rect":[0,0,1,1],"materialAsset":null,"autoWidth":false,"autoHeight":false,"useInput":true,"batchGroupId":null,"mask":false,"layers":[4],"enableMarkup":false}}},"6a2df091-c082-4c26-980c-04c5b520708c":{"name":"1","tags":[],"enabled":true,"resource_id":"6a2df091-c082-4c26-980c-04c5b520708c","parent":"ce599b24-b99b-4de5-8396-02a674934054","children":[],"position":[5.551115123125783e-17,0,-500],"rotation":[0,0,0],"scale":[100,1000,1],"components":{"element":{"enabled":true,"type":"image","anchor":[0.5,0.5,0.5,0.5],"pivot":[0.5,0.5],"text":"","key":null,"fontAsset":37001863,"fontSize":32,"minFontSize":8,"maxFontSize":32,"autoFitWidth":false,"autoFitHeight":false,"maxLines":null,"lineHeight":32,"wrapLines":true,"spacing":1,"color":[1,1,1],"opacity":1,"textureAsset":37001908,"spriteAsset":null,"spriteFrame":0,"pixelsPerUnit":null,"width":1,"height":1,"margin":[-0.49999999999999994,-0.5,-0.5,-0.5],"alignment":[0.5,0.5],"outlineColor":[0,0,0,1],"outlineThickness":0,"shadowColor":[0,0,0,1],"shadowOffset":[0,0],"rect":[0,0,1,1],"materialAsset":null,"autoWidth":false,"autoHeight":false,"useInput":true,"batchGroupId":null,"mask":false,"layers":[4],"enableMarkup":false}}},"0dfe5b63-3df0-479f-838c-c276dd86e0f6":{"name":"New Entity","tags":[],"enabled":true,"resource_id":"0dfe5b63-3df0-479f-838c-c276dd86e0f6","parent":"ed3e3211-58fb-40bc-a964-2da44a2761a3","children":["1e3ea927-99f6-4b79-abf3-0f9831c4a223","6020d9b6-ff37-47f1-99d9-33fc28d9124e"],"position":[0,0,0],"rotation":[0,60,0],"scale":[1,1,1],"components":{}},"1e3ea927-99f6-4b79-abf3-0f9831c4a223":{"name":"1","tags":[],"enabled":true,"resource_id":"1e3ea927-99f6-4b79-abf3-0f9831c4a223","parent":"0dfe5b63-3df0-479f-838c-c276dd86e0f6","children":[],"position":[5.551115123125783e-17,0,500],"rotation":[0,180,0],"scale":[100,1000,1],"components":{"element":{"enabled":true,"type":"image","anchor":[0.5,0.5,0.5,0.5],"pivot":[0.5,0.5],"text":"","key":null,"fontAsset":37001863,"fontSize":32,"minFontSize":8,"maxFontSize":32,"autoFitWidth":false,"autoFitHeight":false,"maxLines":null,"lineHeight":32,"wrapLines":true,"spacing":1,"color":[1,1,1],"opacity":1,"textureAsset":37001908,"spriteAsset":null,"spriteFrame":0,"pixelsPerUnit":null,"width":1,"height":1,"margin":[-0.49999999999999994,-0.5,-0.5,-0.5],"alignment":[0.5,0.5],"outlineColor":[0,0,0,1],"outlineThickness":0,"shadowColor":[0,0,0,1],"shadowOffset":[0,0],"rect":[0,0,1,1],"materialAsset":null,"autoWidth":false,"autoHeight":false,"useInput":true,"batchGroupId":null,"mask":false,"layers":[4],"enableMarkup":false}}},"6020d9b6-ff37-47f1-99d9-33fc28d9124e":{"name":"1","tags":[],"enabled":true,"resource_id":"6020d9b6-ff37-47f1-99d9-33fc28d9124e","parent":"0dfe5b63-3df0-479f-838c-c276dd86e0f6","children":[],"position":[5.551115123125783e-17,0,-500],"rotation":[0,0,0],"scale":[100,1000,1],"components":{"element":{"enabled":true,"type":"image","anchor":[0.5,0.5,0.5,0.5],"pivot":[0.5,0.5],"text":"","key":null,"fontAsset":37001863,"fontSize":32,"minFontSize":8,"maxFontSize":32,"autoFitWidth":false,"autoFitHeight":false,"maxLines":null,"lineHeight":32,"wrapLines":true,"spacing":1,"color":[1,1,1],"opacity":1,"textureAsset":37001908,"spriteAsset":null,"spriteFrame":0,"pixelsPerUnit":null,"width":1,"height":1,"margin":[-0.49999999999999994,-0.5,-0.5,-0.5],"alignment":[0.5,0.5],"outlineColor":[0,0,0,1],"outlineThickness":0,"shadowColor":[0,0,0,1],"shadowOffset":[0,0],"rect":[0,0,1,1],"materialAsset":null,"autoWidth":false,"autoHeight":false,"useInput":true,"batchGroupId":null,"mask":false,"layers":[4],"enableMarkup":false}}},"099936bc-0ebe-4b13-be7a-55781719ebe8":{"name":"New Entity","tags":[],"enabled":true,"resource_id":"099936bc-0ebe-4b13-be7a-55781719ebe8","parent":"ed3e3211-58fb-40bc-a964-2da44a2761a3","children":["e0928f3e-e43d-4480-9863-0c1c0782b96c","859e6796-86fd-49bb-bf8c-a0955a71b5bd"],"position":[0,0,0],"rotation":[0,70,0],"scale":[1,1,1],"components":{}},"e0928f3e-e43d-4480-9863-0c1c0782b96c":{"name":"1","tags":[],"enabled":true,"resource_id":"e0928f3e-e43d-4480-9863-0c1c0782b96c","parent":"099936bc-0ebe-4b13-be7a-55781719ebe8","children":[],"position":[5.551115123125783e-17,0,500],"rotation":[0,180,0],"scale":[100,1000,1],"components":{"element":{"enabled":true,"type":"image","anchor":[0.5,0.5,0.5,0.5],"pivot":[0.5,0.5],"text":"","key":null,"fontAsset":37001863,"fontSize":32,"minFontSize":8,"maxFontSize":32,"autoFitWidth":false,"autoFitHeight":false,"maxLines":null,"lineHeight":32,"wrapLines":true,"spacing":1,"color":[1,1,1],"opacity":1,"textureAsset":37001908,"spriteAsset":null,"spriteFrame":0,"pixelsPerUnit":null,"width":1,"height":1,"margin":[-0.49999999999999994,-0.5,-0.5,-0.5],"alignment":[0.5,0.5],"outlineColor":[0,0,0,1],"outlineThickness":0,"shadowColor":[0,0,0,1],"shadowOffset":[0,0],"rect":[0,0,1,1],"materialAsset":null,"autoWidth":false,"autoHeight":false,"useInput":true,"batchGroupId":null,"mask":false,"layers":[4],"enableMarkup":false}}},"859e6796-86fd-49bb-bf8c-a0955a71b5bd":{"name":"1","tags":[],"enabled":true,"resource_id":"859e6796-86fd-49bb-bf8c-a0955a71b5bd","parent":"099936bc-0ebe-4b13-be7a-55781719ebe8","children":[],"position":[5.551115123125783e-17,0,-500],"rotation":[0,0,0],"scale":[100,1000,1],"components":{"element":{"enabled":true,"type":"image","anchor":[0.5,0.5,0.5,0.5],"pivot":[0.5,0.5],"text":"","key":null,"fontAsset":37001863,"fontSize":32,"minFontSize":8,"maxFontSize":32,"autoFitWidth":false,"autoFitHeight":false,"maxLines":null,"lineHeight":32,"wrapLines":true,"spacing":1,"color":[1,1,1],"opacity":1,"textureAsset":37001908,"spriteAsset":null,"spriteFrame":0,"pixelsPerUnit":null,"width":1,"height":1,"margin":[-0.49999999999999994,-0.5,-0.5,-0.5],"alignment":[0.5,0.5],"outlineColor":[0,0,0,1],"outlineThickness":0,"shadowColor":[0,0,0,1],"shadowOffset":[0,0],"rect":[0,0,1,1],"materialAsset":null,"autoWidth":false,"autoHeight":false,"useInput":true,"batchGroupId":null,"mask":false,"layers":[4],"enableMarkup":false}}},"04bb8e44-ed12-4b9f-9c28-4a67a2d11025":{"name":"New Entity","tags":[],"enabled":true,"resource_id":"04bb8e44-ed12-4b9f-9c28-4a67a2d11025","parent":"ed3e3211-58fb-40bc-a964-2da44a2761a3","children":["79193491-ea28-4067-b128-39c3e2678f00","f64b4e83-23bf-49e8-a985-bd20fad43393"],"position":[0,0,0],"rotation":[0,80,0],"scale":[1,1,1],"components":{}},"79193491-ea28-4067-b128-39c3e2678f00":{"name":"1","tags":[],"enabled":true,"resource_id":"79193491-ea28-4067-b128-39c3e2678f00","parent":"04bb8e44-ed12-4b9f-9c28-4a67a2d11025","children":[],"position":[5.551115123125783e-17,0,500],"rotation":[0,180,0],"scale":[100,1000,1],"components":{"element":{"enabled":true,"type":"image","anchor":[0.5,0.5,0.5,0.5],"pivot":[0.5,0.5],"text":"","key":null,"fontAsset":37001863,"fontSize":32,"minFontSize":8,"maxFontSize":32,"autoFitWidth":false,"autoFitHeight":false,"maxLines":null,"lineHeight":32,"wrapLines":true,"spacing":1,"color":[1,1,1],"opacity":1,"textureAsset":37001908,"spriteAsset":null,"spriteFrame":0,"pixelsPerUnit":null,"width":1,"height":1,"margin":[-0.49999999999999994,-0.5,-0.5,-0.5],"alignment":[0.5,0.5],"outlineColor":[0,0,0,1],"outlineThickness":0,"shadowColor":[0,0,0,1],"shadowOffset":[0,0],"rect":[0,0,1,1],"materialAsset":null,"autoWidth":false,"autoHeight":false,"useInput":true,"batchGroupId":null,"mask":false,"layers":[4],"enableMarkup":false}}},"f64b4e83-23bf-49e8-a985-bd20fad43393":{"name":"1","tags":[],"enabled":true,"resource_id":"f64b4e83-23bf-49e8-a985-bd20fad43393","parent":"04bb8e44-ed12-4b9f-9c28-4a67a2d11025","children":[],"position":[5.551115123125783e-17,0,-500],"rotation":[0,0,0],"scale":[100,1000,1],"components":{"element":{"enabled":true,"type":"image","anchor":[0.5,0.5,0.5,0.5],"pivot":[0.5,0.5],"text":"","key":null,"fontAsset":37001863,"fontSize":32,"minFontSize":8,"maxFontSize":32,"autoFitWidth":false,"autoFitHeight":false,"maxLines":null,"lineHeight":32,"wrapLines":true,"spacing":1,"color":[1,1,1],"opacity":1,"textureAsset":37001908,"spriteAsset":null,"spriteFrame":0,"pixelsPerUnit":null,"width":1,"height":1,"margin":[-0.49999999999999994,-0.5,-0.5,-0.5],"alignment":[0.5,0.5],"outlineColor":[0,0,0,1],"outlineThickness":0,"shadowColor":[0,0,0,1],"shadowOffset":[0,0],"rect":[0,0,1,1],"materialAsset":null,"autoWidth":false,"autoHeight":false,"useInput":true,"batchGroupId":null,"mask":false,"layers":[4],"enableMarkup":false}}},"0aa66b53-0aa2-42d5-90c3-462fc49e0142":{"name":"New Entity","tags":[],"enabled":true,"resource_id":"0aa66b53-0aa2-42d5-90c3-462fc49e0142","parent":"ed3e3211-58fb-40bc-a964-2da44a2761a3","children":["737b54df-bc4b-4f11-a5a8-aee01b05b4ec","a5de1b39-f238-4e93-811b-b230cd0120ca"],"position":[0,0,0],"rotation":[0,90,0],"scale":[1,1,1],"components":{}},"737b54df-bc4b-4f11-a5a8-aee01b05b4ec":{"name":"1","tags":[],"enabled":true,"resource_id":"737b54df-bc4b-4f11-a5a8-aee01b05b4ec","parent":"0aa66b53-0aa2-42d5-90c3-462fc49e0142","children":[],"position":[5.551115123125783e-17,0,500],"rotation":[0,180,0],"scale":[100,1000,1],"components":{"element":{"enabled":true,"type":"image","anchor":[0.5,0.5,0.5,0.5],"pivot":[0.5,0.5],"text":"","key":null,"fontAsset":37001863,"fontSize":32,"minFontSize":8,"maxFontSize":32,"autoFitWidth":false,"autoFitHeight":false,"maxLines":null,"lineHeight":32,"wrapLines":true,"spacing":1,"color":[1,1,1],"opacity":1,"textureAsset":37001908,"spriteAsset":null,"spriteFrame":0,"pixelsPerUnit":null,"width":1,"height":1,"margin":[-0.49999999999999994,-0.5,-0.5,-0.5],"alignment":[0.5,0.5],"outlineColor":[0,0,0,1],"outlineThickness":0,"shadowColor":[0,0,0,1],"shadowOffset":[0,0],"rect":[0,0,1,1],"materialAsset":null,"autoWidth":false,"autoHeight":false,"useInput":true,"batchGroupId":null,"mask":false,"layers":[4],"enableMarkup":false}}},"a5de1b39-f238-4e93-811b-b230cd0120ca":{"name":"1","tags":[],"enabled":true,"resource_id":"a5de1b39-f238-4e93-811b-b230cd0120ca","parent":"0aa66b53-0aa2-42d5-90c3-462fc49e0142","children":[],"position":[5.551115123125783e-17,0,-500],"rotation":[0,0,0],"scale":[100,1000,1],"components":{"element":{"enabled":true,"type":"image","anchor":[0.5,0.5,0.5,0.5],"pivot":[0.5,0.5],"text":"","key":null,"fontAsset":37001863,"fontSize":32,"minFontSize":8,"maxFontSize":32,"autoFitWidth":false,"autoFitHeight":false,"maxLines":null,"lineHeight":32,"wrapLines":true,"spacing":1,"color":[1,1,1],"opacity":1,"textureAsset":37001908,"spriteAsset":null,"spriteFrame":0,"pixelsPerUnit":null,"width":1,"height":1,"margin":[-0.49999999999999994,-0.5,-0.5,-0.5],"alignment":[0.5,0.5],"outlineColor":[0,0,0,1],"outlineThickness":0,"shadowColor":[0,0,0,1],"shadowOffset":[0,0],"rect":[0,0,1,1],"materialAsset":null,"autoWidth":false,"autoHeight":false,"useInput":true,"batchGroupId":null,"mask":false,"layers":[4],"enableMarkup":false}}},"4b670b2c-16a9-4ba5-850c-ef9f6fbbde0e":{"name":"New Entity","tags":[],"enabled":true,"resource_id":"4b670b2c-16a9-4ba5-850c-ef9f6fbbde0e","parent":"ed3e3211-58fb-40bc-a964-2da44a2761a3","children":["c02d1632-efb8-4eb9-9ebf-19a8f48f84f0","5e126aa7-4896-404d-805e-77320bbc1a9e"],"position":[0,0,0],"rotation":[0,100,0],"scale":[1,1,1],"components":{}},"c02d1632-efb8-4eb9-9ebf-19a8f48f84f0":{"name":"1","tags":[],"enabled":true,"resource_id":"c02d1632-efb8-4eb9-9ebf-19a8f48f84f0","parent":"4b670b2c-16a9-4ba5-850c-ef9f6fbbde0e","children":[],"position":[5.551115123125783e-17,0,500],"rotation":[0,180,0],"scale":[100,1000,1],"components":{"element":{"enabled":true,"type":"image","anchor":[0.5,0.5,0.5,0.5],"pivot":[0.5,0.5],"text":"","key":null,"fontAsset":37001863,"fontSize":32,"minFontSize":8,"maxFontSize":32,"autoFitWidth":false,"autoFitHeight":false,"maxLines":null,"lineHeight":32,"wrapLines":true,"spacing":1,"color":[1,1,1],"opacity":1,"textureAsset":37001908,"spriteAsset":null,"spriteFrame":0,"pixelsPerUnit":null,"width":1,"height":1,"margin":[-0.49999999999999994,-0.5,-0.5,-0.5],"alignment":[0.5,0.5],"outlineColor":[0,0,0,1],"outlineThickness":0,"shadowColor":[0,0,0,1],"shadowOffset":[0,0],"rect":[0,0,1,1],"materialAsset":null,"autoWidth":false,"autoHeight":false,"useInput":true,"batchGroupId":null,"mask":false,"layers":[4],"enableMarkup":false}}},"5e126aa7-4896-404d-805e-77320bbc1a9e":{"name":"1","tags":[],"enabled":true,"resource_id":"5e126aa7-4896-404d-805e-77320bbc1a9e","parent":"4b670b2c-16a9-4ba5-850c-ef9f6fbbde0e","children":[],"position":[5.551115123125783e-17,0,-500],"rotation":[0,0,0],"scale":[100,1000,1],"components":{"element":{"enabled":true,"type":"image","anchor":[0.5,0.5,0.5,0.5],"pivot":[0.5,0.5],"text":"","key":null,"fontAsset":37001863,"fontSize":32,"minFontSize":8,"maxFontSize":32,"autoFitWidth":false,"autoFitHeight":false,"maxLines":null,"lineHeight":32,"wrapLines":true,"spacing":1,"color":[1,1,1],"opacity":1,"textureAsset":37001908,"spriteAsset":null,"spriteFrame":0,"pixelsPerUnit":null,"width":1,"height":1,"margin":[-0.49999999999999994,-0.5,-0.5,-0.5],"alignment":[0.5,0.5],"outlineColor":[0,0,0,1],"outlineThickness":0,"shadowColor":[0,0,0,1],"shadowOffset":[0,0],"rect":[0,0,1,1],"materialAsset":null,"autoWidth":false,"autoHeight":false,"useInput":true,"batchGroupId":null,"mask":false,"layers":[4],"enableMarkup":false}}},"ac06fc86-e14f-4fc6-a431-d94d2e5eba0d":{"name":"New Entity","tags":[],"enabled":true,"resource_id":"ac06fc86-e14f-4fc6-a431-d94d2e5eba0d","parent":"ed3e3211-58fb-40bc-a964-2da44a2761a3","children":["615d9d41-4774-455a-a7cd-32c2f9622b67","956193a3-1400-49f4-828e-69968a8059f4"],"position":[0,0,0],"rotation":[0,110,0],"scale":[1,1,1],"components":{}},"615d9d41-4774-455a-a7cd-32c2f9622b67":{"name":"1","tags":[],"enabled":true,"resource_id":"615d9d41-4774-455a-a7cd-32c2f9622b67","parent":"ac06fc86-e14f-4fc6-a431-d94d2e5eba0d","children":[],"position":[5.551115123125783e-17,0,500],"rotation":[0,180,0],"scale":[100,1000,1],"components":{"element":{"enabled":true,"type":"image","anchor":[0.5,0.5,0.5,0.5],"pivot":[0.5,0.5],"text":"","key":null,"fontAsset":37001863,"fontSize":32,"minFontSize":8,"maxFontSize":32,"autoFitWidth":false,"autoFitHeight":false,"maxLines":null,"lineHeight":32,"wrapLines":true,"spacing":1,"color":[1,1,1],"opacity":1,"textureAsset":37001908,"spriteAsset":null,"spriteFrame":0,"pixelsPerUnit":null,"width":1,"height":1,"margin":[-0.49999999999999994,-0.5,-0.5,-0.5],"alignment":[0.5,0.5],"outlineColor":[0,0,0,1],"outlineThickness":0,"shadowColor":[0,0,0,1],"shadowOffset":[0,0],"rect":[0,0,1,1],"materialAsset":null,"autoWidth":false,"autoHeight":false,"useInput":true,"batchGroupId":null,"mask":false,"layers":[4],"enableMarkup":false}}},"956193a3-1400-49f4-828e-69968a8059f4":{"name":"1","tags":[],"enabled":true,"resource_id":"956193a3-1400-49f4-828e-69968a8059f4","parent":"ac06fc86-e14f-4fc6-a431-d94d2e5eba0d","children":[],"position":[5.551115123125783e-17,0,-500],"rotation":[0,0,0],"scale":[100,1000,1],"components":{"element":{"enabled":true,"type":"image","anchor":[0.5,0.5,0.5,0.5],"pivot":[0.5,0.5],"text":"","key":null,"fontAsset":37001863,"fontSize":32,"minFontSize":8,"maxFontSize":32,"autoFitWidth":false,"autoFitHeight":false,"maxLines":null,"lineHeight":32,"wrapLines":true,"spacing":1,"color":[1,1,1],"opacity":1,"textureAsset":37001908,"spriteAsset":null,"spriteFrame":0,"pixelsPerUnit":null,"width":1,"height":1,"margin":[-0.49999999999999994,-0.5,-0.5,-0.5],"alignment":[0.5,0.5],"outlineColor":[0,0,0,1],"outlineThickness":0,"shadowColor":[0,0,0,1],"shadowOffset":[0,0],"rect":[0,0,1,1],"materialAsset":null,"autoWidth":false,"autoHeight":false,"useInput":true,"batchGroupId":null,"mask":false,"layers":[4],"enableMarkup":false}}},"0c011034-3b01-4fb1-81ce-929aea98acb5":{"name":"New Entity","tags":[],"enabled":true,"resource_id":"0c011034-3b01-4fb1-81ce-929aea98acb5","parent":"ed3e3211-58fb-40bc-a964-2da44a2761a3","children":["d1aee154-631d-4cbd-8cf0-6dabc2c765b2","f1b17508-6739-45bf-8414-e3e0db98c389"],"position":[0,0,0],"rotation":[0,120,0],"scale":[1,1,1],"components":{}},"d1aee154-631d-4cbd-8cf0-6dabc2c765b2":{"name":"1","tags":[],"enabled":true,"resource_id":"d1aee154-631d-4cbd-8cf0-6dabc2c765b2","parent":"0c011034-3b01-4fb1-81ce-929aea98acb5","children":[],"position":[5.551115123125783e-17,0,500],"rotation":[0,180,0],"scale":[100,1000,1],"components":{"element":{"enabled":true,"type":"image","anchor":[0.5,0.5,0.5,0.5],"pivot":[0.5,0.5],"text":"","key":null,"fontAsset":37001863,"fontSize":32,"minFontSize":8,"maxFontSize":32,"autoFitWidth":false,"autoFitHeight":false,"maxLines":null,"lineHeight":32,"wrapLines":true,"spacing":1,"color":[1,1,1],"opacity":1,"textureAsset":37001908,"spriteAsset":null,"spriteFrame":0,"pixelsPerUnit":null,"width":1,"height":1,"margin":[-0.49999999999999994,-0.5,-0.5,-0.5],"alignment":[0.5,0.5],"outlineColor":[0,0,0,1],"outlineThickness":0,"shadowColor":[0,0,0,1],"shadowOffset":[0,0],"rect":[0,0,1,1],"materialAsset":null,"autoWidth":false,"autoHeight":false,"useInput":true,"batchGroupId":null,"mask":false,"layers":[4],"enableMarkup":false}}},"f1b17508-6739-45bf-8414-e3e0db98c389":{"name":"1","tags":[],"enabled":true,"resource_id":"f1b17508-6739-45bf-8414-e3e0db98c389","parent":"0c011034-3b01-4fb1-81ce-929aea98acb5","children":[],"position":[5.551115123125783e-17,0,-500],"rotation":[0,0,0],"scale":[100,1000,1],"components":{"element":{"enabled":true,"type":"image","anchor":[0.5,0.5,0.5,0.5],"pivot":[0.5,0.5],"text":"","key":null,"fontAsset":37001863,"fontSize":32,"minFontSize":8,"maxFontSize":32,"autoFitWidth":false,"autoFitHeight":false,"maxLines":null,"lineHeight":32,"wrapLines":true,"spacing":1,"color":[1,1,1],"opacity":1,"textureAsset":37001908,"spriteAsset":null,"spriteFrame":0,"pixelsPerUnit":null,"width":1,"height":1,"margin":[-0.49999999999999994,-0.5,-0.5,-0.5],"alignment":[0.5,0.5],"outlineColor":[0,0,0,1],"outlineThickness":0,"shadowColor":[0,0,0,1],"shadowOffset":[0,0],"rect":[0,0,1,1],"materialAsset":null,"autoWidth":false,"autoHeight":false,"useInput":true,"batchGroupId":null,"mask":false,"layers":[4],"enableMarkup":false}}},"9e3a5731-0201-48bb-b07c-84b5f4837b3b":{"name":"New Entity","tags":[],"enabled":true,"resource_id":"9e3a5731-0201-48bb-b07c-84b5f4837b3b","parent":"ed3e3211-58fb-40bc-a964-2da44a2761a3","children":["008f4359-5c8a-4cd5-96be-34d72d3fdc88","d4e23ab9-8457-474c-adb4-c679b5e6d8c3"],"position":[0,0,0],"rotation":[0,130,0],"scale":[1,1,1],"components":{}},"008f4359-5c8a-4cd5-96be-34d72d3fdc88":{"name":"1","tags":[],"enabled":true,"resource_id":"008f4359-5c8a-4cd5-96be-34d72d3fdc88","parent":"9e3a5731-0201-48bb-b07c-84b5f4837b3b","children":[],"position":[5.551115123125783e-17,0,500],"rotation":[0,180,0],"scale":[100,1000,1],"components":{"element":{"enabled":true,"type":"image","anchor":[0.5,0.5,0.5,0.5],"pivot":[0.5,0.5],"text":"","key":null,"fontAsset":37001863,"fontSize":32,"minFontSize":8,"maxFontSize":32,"autoFitWidth":false,"autoFitHeight":false,"maxLines":null,"lineHeight":32,"wrapLines":true,"spacing":1,"color":[1,1,1],"opacity":1,"textureAsset":37001908,"spriteAsset":null,"spriteFrame":0,"pixelsPerUnit":null,"width":1,"height":1,"margin":[-0.49999999999999994,-0.5,-0.5,-0.5],"alignment":[0.5,0.5],"outlineColor":[0,0,0,1],"outlineThickness":0,"shadowColor":[0,0,0,1],"shadowOffset":[0,0],"rect":[0,0,1,1],"materialAsset":null,"autoWidth":false,"autoHeight":false,"useInput":true,"batchGroupId":null,"mask":false,"layers":[4],"enableMarkup":false}}},"d4e23ab9-8457-474c-adb4-c679b5e6d8c3":{"name":"1","tags":[],"enabled":true,"resource_id":"d4e23ab9-8457-474c-adb4-c679b5e6d8c3","parent":"9e3a5731-0201-48bb-b07c-84b5f4837b3b","children":[],"position":[5.551115123125783e-17,0,-500],"rotation":[0,0,0],"scale":[100,1000,1],"components":{"element":{"enabled":true,"type":"image","anchor":[0.5,0.5,0.5,0.5],"pivot":[0.5,0.5],"text":"","key":null,"fontAsset":37001863,"fontSize":32,"minFontSize":8,"maxFontSize":32,"autoFitWidth":false,"autoFitHeight":false,"maxLines":null,"lineHeight":32,"wrapLines":true,"spacing":1,"color":[1,1,1],"opacity":1,"textureAsset":37001908,"spriteAsset":null,"spriteFrame":0,"pixelsPerUnit":null,"width":1,"height":1,"margin":[-0.49999999999999994,-0.5,-0.5,-0.5],"alignment":[0.5,0.5],"outlineColor":[0,0,0,1],"outlineThickness":0,"shadowColor":[0,0,0,1],"shadowOffset":[0,0],"rect":[0,0,1,1],"materialAsset":null,"autoWidth":false,"autoHeight":false,"useInput":true,"batchGroupId":null,"mask":false,"layers":[4],"enableMarkup":false}}},"6cf5bbef-5765-407f-88ca-b4a061b17124":{"name":"New Entity","tags":[],"enabled":true,"resource_id":"6cf5bbef-5765-407f-88ca-b4a061b17124","parent":"ed3e3211-58fb-40bc-a964-2da44a2761a3","children":["f00ec784-00df-4219-9ada-97e29a52eab4","0fb345af-d5aa-421d-9418-3be3fabe68ad"],"position":[0,0,0],"rotation":[0,140,0],"scale":[1,1,1],"components":{}},"f00ec784-00df-4219-9ada-97e29a52eab4":{"name":"1","tags":[],"enabled":true,"resource_id":"f00ec784-00df-4219-9ada-97e29a52eab4","parent":"6cf5bbef-5765-407f-88ca-b4a061b17124","children":[],"position":[5.551115123125783e-17,0,500],"rotation":[0,180,0],"scale":[100,1000,1],"components":{"element":{"enabled":true,"type":"image","anchor":[0.5,0.5,0.5,0.5],"pivot":[0.5,0.5],"text":"","key":null,"fontAsset":37001863,"fontSize":32,"minFontSize":8,"maxFontSize":32,"autoFitWidth":false,"autoFitHeight":false,"maxLines":null,"lineHeight":32,"wrapLines":true,"spacing":1,"color":[1,1,1],"opacity":1,"textureAsset":37001908,"spriteAsset":null,"spriteFrame":0,"pixelsPerUnit":null,"width":1,"height":1,"margin":[-0.49999999999999994,-0.5,-0.5,-0.5],"alignment":[0.5,0.5],"outlineColor":[0,0,0,1],"outlineThickness":0,"shadowColor":[0,0,0,1],"shadowOffset":[0,0],"rect":[0,0,1,1],"materialAsset":null,"autoWidth":false,"autoHeight":false,"useInput":true,"batchGroupId":null,"mask":false,"layers":[4],"enableMarkup":false}}},"0fb345af-d5aa-421d-9418-3be3fabe68ad":{"name":"1","tags":[],"enabled":true,"resource_id":"0fb345af-d5aa-421d-9418-3be3fabe68ad","parent":"6cf5bbef-5765-407f-88ca-b4a061b17124","children":[],"position":[5.551115123125783e-17,0,-500],"rotation":[0,0,0],"scale":[100,1000,1],"components":{"element":{"enabled":true,"type":"image","anchor":[0.5,0.5,0.5,0.5],"pivot":[0.5,0.5],"text":"","key":null,"fontAsset":37001863,"fontSize":32,"minFontSize":8,"maxFontSize":32,"autoFitWidth":false,"autoFitHeight":false,"maxLines":null,"lineHeight":32,"wrapLines":true,"spacing":1,"color":[1,1,1],"opacity":1,"textureAsset":37001908,"spriteAsset":null,"spriteFrame":0,"pixelsPerUnit":null,"width":1,"height":1,"margin":[-0.49999999999999994,-0.5,-0.5,-0.5],"alignment":[0.5,0.5],"outlineColor":[0,0,0,1],"outlineThickness":0,"shadowColor":[0,0,0,1],"shadowOffset":[0,0],"rect":[0,0,1,1],"materialAsset":null,"autoWidth":false,"autoHeight":false,"useInput":true,"batchGroupId":null,"mask":false,"layers":[4],"enableMarkup":false}}},"37c681b2-efde-4ccc-931b-35e3b000a69e":{"name":"New Entity","tags":[],"enabled":true,"resource_id":"37c681b2-efde-4ccc-931b-35e3b000a69e","parent":"ed3e3211-58fb-40bc-a964-2da44a2761a3","children":["4ec657f8-0f1e-46ed-81a9-80857ced9d46","c0856aae-2ff6-4acf-b886-8088df2c6414"],"position":[0,0,0],"rotation":[0,150,0],"scale":[1,1,1],"components":{}},"4ec657f8-0f1e-46ed-81a9-80857ced9d46":{"name":"1","tags":[],"enabled":true,"resource_id":"4ec657f8-0f1e-46ed-81a9-80857ced9d46","parent":"37c681b2-efde-4ccc-931b-35e3b000a69e","children":[],"position":[5.551115123125783e-17,0,500],"rotation":[0,180,0],"scale":[100,1000,1],"components":{"element":{"enabled":true,"type":"image","anchor":[0.5,0.5,0.5,0.5],"pivot":[0.5,0.5],"text":"","key":null,"fontAsset":37001863,"fontSize":32,"minFontSize":8,"maxFontSize":32,"autoFitWidth":false,"autoFitHeight":false,"maxLines":null,"lineHeight":32,"wrapLines":true,"spacing":1,"color":[1,1,1],"opacity":1,"textureAsset":37001908,"spriteAsset":null,"spriteFrame":0,"pixelsPerUnit":null,"width":1,"height":1,"margin":[-0.49999999999999994,-0.5,-0.5,-0.5],"alignment":[0.5,0.5],"outlineColor":[0,0,0,1],"outlineThickness":0,"shadowColor":[0,0,0,1],"shadowOffset":[0,0],"rect":[0,0,1,1],"materialAsset":null,"autoWidth":false,"autoHeight":false,"useInput":true,"batchGroupId":null,"mask":false,"layers":[4],"enableMarkup":false}}},"c0856aae-2ff6-4acf-b886-8088df2c6414":{"name":"1","tags":[],"enabled":true,"resource_id":"c0856aae-2ff6-4acf-b886-8088df2c6414","parent":"37c681b2-efde-4ccc-931b-35e3b000a69e","children":[],"position":[5.551115123125783e-17,0,-500],"rotation":[0,0,0],"scale":[100,1000,1],"components":{"element":{"enabled":true,"type":"image","anchor":[0.5,0.5,0.5,0.5],"pivot":[0.5,0.5],"text":"","key":null,"fontAsset":37001863,"fontSize":32,"minFontSize":8,"maxFontSize":32,"autoFitWidth":false,"autoFitHeight":false,"maxLines":null,"lineHeight":32,"wrapLines":true,"spacing":1,"color":[1,1,1],"opacity":1,"textureAsset":37001908,"spriteAsset":null,"spriteFrame":0,"pixelsPerUnit":null,"width":1,"height":1,"margin":[-0.49999999999999994,-0.5,-0.5,-0.5],"alignment":[0.5,0.5],"outlineColor":[0,0,0,1],"outlineThickness":0,"shadowColor":[0,0,0,1],"shadowOffset":[0,0],"rect":[0,0,1,1],"materialAsset":null,"autoWidth":false,"autoHeight":false,"useInput":true,"batchGroupId":null,"mask":false,"layers":[4],"enableMarkup":false}}},"32a31714-1fce-4259-bfa8-fb86b5dbb16c":{"name":"New Entity","tags":[],"enabled":true,"resource_id":"32a31714-1fce-4259-bfa8-fb86b5dbb16c","parent":"ed3e3211-58fb-40bc-a964-2da44a2761a3","children":["976e8860-5fee-4fef-8401-dec0dcecdfbd","e31ff70c-e2c8-4feb-9a18-bd0badc05b3d"],"position":[0,0,0],"rotation":[0,160,0],"scale":[1,1,1],"components":{}},"976e8860-5fee-4fef-8401-dec0dcecdfbd":{"name":"1","tags":[],"enabled":true,"resource_id":"976e8860-5fee-4fef-8401-dec0dcecdfbd","parent":"32a31714-1fce-4259-bfa8-fb86b5dbb16c","children":[],"position":[5.551115123125783e-17,0,500],"rotation":[0,180,0],"scale":[100,1000,1],"components":{"element":{"enabled":true,"type":"image","anchor":[0.5,0.5,0.5,0.5],"pivot":[0.5,0.5],"text":"","key":null,"fontAsset":37001863,"fontSize":32,"minFontSize":8,"maxFontSize":32,"autoFitWidth":false,"autoFitHeight":false,"maxLines":null,"lineHeight":32,"wrapLines":true,"spacing":1,"color":[1,1,1],"opacity":1,"textureAsset":37001908,"spriteAsset":null,"spriteFrame":0,"pixelsPerUnit":null,"width":1,"height":1,"margin":[-0.49999999999999994,-0.5,-0.5,-0.5],"alignment":[0.5,0.5],"outlineColor":[0,0,0,1],"outlineThickness":0,"shadowColor":[0,0,0,1],"shadowOffset":[0,0],"rect":[0,0,1,1],"materialAsset":null,"autoWidth":false,"autoHeight":false,"useInput":true,"batchGroupId":null,"mask":false,"layers":[4],"enableMarkup":false}}},"e31ff70c-e2c8-4feb-9a18-bd0badc05b3d":{"name":"1","tags":[],"enabled":true,"resource_id":"e31ff70c-e2c8-4feb-9a18-bd0badc05b3d","parent":"32a31714-1fce-4259-bfa8-fb86b5dbb16c","children":[],"position":[5.551115123125783e-17,0,-500],"rotation":[0,0,0],"scale":[100,1000,1],"components":{"element":{"enabled":true,"type":"image","anchor":[0.5,0.5,0.5,0.5],"pivot":[0.5,0.5],"text":"","key":null,"fontAsset":37001863,"fontSize":32,"minFontSize":8,"maxFontSize":32,"autoFitWidth":false,"autoFitHeight":false,"maxLines":null,"lineHeight":32,"wrapLines":true,"spacing":1,"color":[1,1,1],"opacity":1,"textureAsset":37001908,"spriteAsset":null,"spriteFrame":0,"pixelsPerUnit":null,"width":1,"height":1,"margin":[-0.49999999999999994,-0.5,-0.5,-0.5],"alignment":[0.5,0.5],"outlineColor":[0,0,0,1],"outlineThickness":0,"shadowColor":[0,0,0,1],"shadowOffset":[0,0],"rect":[0,0,1,1],"materialAsset":null,"autoWidth":false,"autoHeight":false,"useInput":true,"batchGroupId":null,"mask":false,"layers":[4],"enableMarkup":false}}},"388ad753-ceb3-436f-b0c1-0b47c3bb121f":{"name":"New Entity","tags":[],"enabled":true,"resource_id":"388ad753-ceb3-436f-b0c1-0b47c3bb121f","parent":"ed3e3211-58fb-40bc-a964-2da44a2761a3","children":["cd65559f-5ec5-4147-b543-bd476ecc38b1","0cac0d16-6eed-4b2b-adc5-e9309b13ecdc"],"position":[0,0,0],"rotation":[0,170,0],"scale":[1,1,1],"components":{}},"cd65559f-5ec5-4147-b543-bd476ecc38b1":{"name":"1","tags":[],"enabled":true,"resource_id":"cd65559f-5ec5-4147-b543-bd476ecc38b1","parent":"388ad753-ceb3-436f-b0c1-0b47c3bb121f","children":[],"position":[5.551115123125783e-17,0,500],"rotation":[0,180,0],"scale":[100,1000,1],"components":{"element":{"enabled":true,"type":"image","anchor":[0.5,0.5,0.5,0.5],"pivot":[0.5,0.5],"text":"","key":null,"fontAsset":37001863,"fontSize":32,"minFontSize":8,"maxFontSize":32,"autoFitWidth":false,"autoFitHeight":false,"maxLines":null,"lineHeight":32,"wrapLines":true,"spacing":1,"color":[1,1,1],"opacity":1,"textureAsset":37001908,"spriteAsset":null,"spriteFrame":0,"pixelsPerUnit":null,"width":1,"height":1,"margin":[-0.49999999999999994,-0.5,-0.5,-0.5],"alignment":[0.5,0.5],"outlineColor":[0,0,0,1],"outlineThickness":0,"shadowColor":[0,0,0,1],"shadowOffset":[0,0],"rect":[0,0,1,1],"materialAsset":null,"autoWidth":false,"autoHeight":false,"useInput":true,"batchGroupId":null,"mask":false,"layers":[4],"enableMarkup":false}}},"0cac0d16-6eed-4b2b-adc5-e9309b13ecdc":{"name":"1","tags":[],"enabled":true,"resource_id":"0cac0d16-6eed-4b2b-adc5-e9309b13ecdc","parent":"388ad753-ceb3-436f-b0c1-0b47c3bb121f","children":[],"position":[5.551115123125783e-17,0,-500],"rotation":[0,0,0],"scale":[100,1000,1],"components":{"element":{"enabled":true,"type":"image","anchor":[0.5,0.5,0.5,0.5],"pivot":[0.5,0.5],"text":"","key":null,"fontAsset":37001863,"fontSize":32,"minFontSize":8,"maxFontSize":32,"autoFitWidth":false,"autoFitHeight":false,"maxLines":null,"lineHeight":32,"wrapLines":true,"spacing":1,"color":[1,1,1],"opacity":1,"textureAsset":37001908,"spriteAsset":null,"spriteFrame":0,"pixelsPerUnit":null,"width":1,"height":1,"margin":[-0.49999999999999994,-0.5,-0.5,-0.5],"alignment":[0.5,0.5],"outlineColor":[0,0,0,1],"outlineThickness":0,"shadowColor":[0,0,0,1],"shadowOffset":[0,0],"rect":[0,0,1,1],"materialAsset":null,"autoWidth":false,"autoHeight":false,"useInput":true,"batchGroupId":null,"mask":false,"layers":[4],"enableMarkup":false}}},"32b5959f-8436-48de-acf6-c278dc3b08de":{"name":"New Entity","tags":[],"enabled":true,"resource_id":"32b5959f-8436-48de-acf6-c278dc3b08de","parent":"ed3e3211-58fb-40bc-a964-2da44a2761a3","children":["133d06e7-2b92-42bf-91a8-c3e7a5061507","1da3b7dd-bc45-4115-b27d-fe23210028d7"],"position":[0,0,0],"rotation":[0,0,0],"scale":[1,1,1],"components":{}},"133d06e7-2b92-42bf-91a8-c3e7a5061507":{"name":"1","tags":[],"enabled":true,"resource_id":"133d06e7-2b92-42bf-91a8-c3e7a5061507","parent":"32b5959f-8436-48de-acf6-c278dc3b08de","children":[],"position":[0,490,-2.220446049250313e-16],"rotation":[90,-4.317538228957986e-15,1.3552764488364585e-14],"scale":[1000,1000,1],"components":{"element":{"enabled":true,"type":"image","anchor":[0.5,0.5,0.5,0.5],"pivot":[0.5,0.5],"text":"","key":null,"fontAsset":37001863,"fontSize":32,"minFontSize":8,"maxFontSize":32,"autoFitWidth":false,"autoFitHeight":false,"maxLines":null,"lineHeight":32,"wrapLines":true,"spacing":1,"color":[0,0,0],"opacity":1,"textureAsset":null,"spriteAsset":null,"spriteFrame":0,"pixelsPerUnit":null,"width":1,"height":1,"margin":[-0.5,489.5,-0.5,-490.5],"alignment":[0.5,0.5],"outlineColor":[0,0,0,1],"outlineThickness":0,"shadowColor":[0,0,0,1],"shadowOffset":[0,0],"rect":[0,0,1,1],"materialAsset":null,"autoWidth":false,"autoHeight":false,"useInput":true,"batchGroupId":null,"mask":false,"layers":[4],"enableMarkup":false}}},"1da3b7dd-bc45-4115-b27d-fe23210028d7":{"name":"1","tags":[],"enabled":true,"resource_id":"1da3b7dd-bc45-4115-b27d-fe23210028d7","parent":"32b5959f-8436-48de-acf6-c278dc3b08de","children":[],"position":[-1,-490,-2.220446049250313e-16],"rotation":[-90,-4.317538228957986e-15,1.3552764488364585e-14],"scale":[1000,1000,1],"components":{"element":{"enabled":true,"type":"image","anchor":[0.5,0.5,0.5,0.5],"pivot":[0.5,0.5],"text":"","key":null,"fontAsset":37001863,"fontSize":32,"minFontSize":8,"maxFontSize":32,"autoFitWidth":false,"autoFitHeight":false,"maxLines":null,"lineHeight":32,"wrapLines":true,"spacing":1,"color":[0,1,0],"opacity":1,"textureAsset":null,"spriteAsset":null,"spriteFrame":0,"pixelsPerUnit":null,"width":1,"height":1,"margin":[-1.5,-490.5,0.5,489.5],"alignment":[0.5,0.5],"outlineColor":[0,0,0,1],"outlineThickness":0,"shadowColor":[0,0,0,1],"shadowOffset":[0,0],"rect":[0,0,1,1],"materialAsset":null,"autoWidth":false,"autoHeight":false,"useInput":true,"batchGroupId":null,"mask":false,"layers":[4],"enableMarkup":false}}},"9c02d825-555b-42df-bd40-c86b2e1ab08e":{"name":"Box","parent":"46e49d6b-35b4-4ad4-9ac2-b8c00927a650","resource_id":"9c02d825-555b-42df-bd40-c86b2e1ab08e","tags":[],"enabled":true,"components":{"model":{"enabled":true,"type":"box","asset":null,"materialAsset":37001986,"castShadows":true,"receiveShadows":true,"lightmapped":false,"lightmapSizeMultiplier":1,"castShadowsLightmap":true,"isStatic":false,"layers":[0],"batchGroupId":null},"collision":{"enabled":true,"type":"box","halfExtents":[1,1.5,0.05],"radius":0.5,"axis":1,"height":2,"asset":null},"script":{"enabled":true,"order":["Bonus"],"scripts":{"Bonus":{"enabled":true,"attributes":{}}}}},"scale":[2,3,0.1],"position":[0,1.5,-9],"rotation":[0,0,0],"children":[]},"3b5213a5-e529-4c14-9b61-5ff8d2ad8ddc":{"name":"Box","parent":"46e49d6b-35b4-4ad4-9ac2-b8c00927a650","resource_id":"3b5213a5-e529-4c14-9b61-5ff8d2ad8ddc","tags":[],"enabled":true,"components":{"model":{"enabled":true,"type":"box","asset":null,"materialAsset":37001967,"castShadows":true,"receiveShadows":true,"lightmapped":false,"lightmapSizeMultiplier":1,"castShadowsLightmap":true,"isStatic":false,"layers":[0],"batchGroupId":null},"rigidbody":{"enabled":true,"type":"static","mass":1,"linearDamping":0,"angularDamping":0,"linearFactor":[1,1,1],"angularFactor":[1,1,1],"friction":0.5,"restitution":0.5},"collision":{"enabled":true,"type":"box","halfExtents":[9,9,0],"radius":0.5,"axis":1,"height":2,"asset":null}},"scale":[18,18,0.001],"position":[0,9,9],"rotation":[0,0,0],"children":[]},"4fb0262e-d17a-46b1-806b-89185da2d62e":{"name":"Box","parent":"46e49d6b-35b4-4ad4-9ac2-b8c00927a650","resource_id":"4fb0262e-d17a-46b1-806b-89185da2d62e","tags":[],"enabled":true,"components":{"model":{"enabled":true,"type":"box","asset":null,"materialAsset":37001967,"castShadows":true,"receiveShadows":true,"lightmapped":false,"lightmapSizeMultiplier":1,"castShadowsLightmap":true,"isStatic":false,"layers":[0],"batchGroupId":null},"rigidbody":{"enabled":true,"type":"static","mass":1,"linearDamping":0,"angularDamping":0,"linearFactor":[1,1,1],"angularFactor":[1,1,1],"friction":0.5,"restitution":0.5},"collision":{"enabled":true,"type":"box","halfExtents":[0,9,9],"radius":0.5,"axis":1,"height":2,"asset":null}},"scale":[0.001,18,18],"position":[9,9,0],"rotation":[0,0,0],"children":[]},"6bd1865c-6f49-4a41-bb16-488d48af0d94":{"name":"Box","parent":"46e49d6b-35b4-4ad4-9ac2-b8c00927a650","resource_id":"6bd1865c-6f49-4a41-bb16-488d48af0d94","tags":[],"enabled":true,"components":{"model":{"enabled":true,"type":"box","asset":null,"materialAsset":37001967,"castShadows":true,"receiveShadows":true,"lightmapped":false,"lightmapSizeMultiplier":1,"castShadowsLightmap":true,"isStatic":false,"layers":[0],"batchGroupId":null},"rigidbody":{"enabled":true,"type":"static","mass":1,"linearDamping":0,"angularDamping":0,"linearFactor":[1,1,1],"angularFactor":[1,1,1],"friction":0.5,"restitution":0.5},"collision":{"enabled":true,"type":"box","halfExtents":[0,9,9],"radius":0.5,"axis":1,"height":2,"asset":null}},"scale":[0.001,18,18],"position":[-9,9,0],"rotation":[0,0,0],"children":[]},"5b05dab5-6cda-46bc-a454-5400446c7118":{"name":"Box","parent":"46e49d6b-35b4-4ad4-9ac2-b8c00927a650","resource_id":"5b05dab5-6cda-46bc-a454-5400446c7118","tags":[],"enabled":true,"components":{"model":{"enabled":true,"type":"box","asset":null,"materialAsset":37001967,"castShadows":true,"receiveShadows":true,"lightmapped":false,"lightmapSizeMultiplier":1,"castShadowsLightmap":true,"isStatic":false,"layers":[0],"batchGroupId":null},"rigidbody":{"enabled":true,"type":"static","mass":1,"linearDamping":0,"angularDamping":0,"linearFactor":[1,1,1],"angularFactor":[1,1,1],"friction":0.5,"restitution":0.5},"collision":{"enabled":true,"type":"box","halfExtents":[9,0,9],"radius":0.5,"axis":1,"height":2,"asset":null}},"scale":[18,0.001,18],"position":[0,18,0],"rotation":[0,0,0],"children":[]},"fbfe8c0e-2716-443e-bacc-2ec772781b05":{"name":"Box","parent":"46e49d6b-35b4-4ad4-9ac2-b8c00927a650","resource_id":"fbfe8c0e-2716-443e-bacc-2ec772781b05","tags":[],"enabled":true,"components":{"model":{"enabled":true,"type":"box","asset":null,"materialAsset":37001954,"castShadows":true,"receiveShadows":true,"lightmapped":false,"lightmapSizeMultiplier":1,"castShadowsLightmap":true,"isStatic":false,"layers":[0],"batchGroupId":null},"rigidbody":{"enabled":true,"type":"static","mass":1,"linearDamping":0,"angularDamping":0,"linearFactor":[1,1,1],"angularFactor":[1,1,1],"friction":0.5,"restitution":0.5},"collision":{"enabled":true,"type":"box","halfExtents":[0.05,0.5,0.05],"radius":0.5,"axis":1,"height":2,"asset":null}},"scale":[0.1,1,0.1],"position":[0,0.5,0],"rotation":[0,0,0],"children":[]},"5254e3bd-d2b9-4bda-8a3b-8d54e05627d2":{"name":"Box","parent":"46e49d6b-35b4-4ad4-9ac2-b8c00927a650","resource_id":"5254e3bd-d2b9-4bda-8a3b-8d54e05627d2","tags":[],"enabled":true,"components":{"model":{"enabled":true,"type":"box","asset":null,"materialAsset":37002005,"castShadows":true,"receiveShadows":true,"lightmapped":false,"lightmapSizeMultiplier":1,"castShadowsLightmap":true,"isStatic":false,"layers":[0],"batchGroupId":null},"rigidbody":{"enabled":true,"type":"static","mass":1,"linearDamping":0,"angularDamping":0,"linearFactor":[1,1,1],"angularFactor":[1,1,1],"friction":0.5,"restitution":0.5},"collision":{"enabled":true,"type":"box","halfExtents":[0.5,0.5,0.05],"radius":0.5,"axis":1,"height":2,"asset":null}},"scale":[1,1,0.1],"position":[0,1.5,0],"rotation":[0,0,0],"children":[]}},"created":"2020-09-05T05:38:24.203Z","id":1015215}